README.md
setup.py
ctype_struct/__init__.py
ctype_struct.egg-info/PKG-INFO
ctype_struct.egg-info/SOURCES.txt
ctype_struct.egg-info/dependency_links.txt
ctype_struct.egg-info/top_level.txt