Metadata-Version: 2.1
Name: ctype-struct
Version: 1.0.1
Summary: python解析C结构体16进制数据.
Home-page: https://github.com/TesterSong/Ctype-Struct-Python.git
Author: songchuhua
Author-email: sch15625785335@163.com
License: MIT
Keywords: C struct
Platform: UNKNOWN
Classifier: Intended Audience :: Developers
Classifier: License :: OSI Approved :: MIT License
Classifier: Natural Language :: English
Classifier: Programming Language :: Python :: 3.7
Requires-Python: >=3.7.0
